.DS_Store
public_data_food_analysis_3/.DS_Store
public_data_food_analysis_3/__init__.py
public_data_food_analysis_3/_nbdev.py
public_data_food_analysis_3/app_data.py
public_data_food_analysis_3/columbia.py
public_data_food_analysis_3/core.py
public_data_food_analysis_3/food_parser.py
public_data_food_analysis_3/data/correction_dic.pickle
public_data_food_analysis_3/data/parser_keys.csv
time_restricted_eating_experiments/__init__.py
time_restricted_eating_experiments/_nbdev.py
time_restricted_eating_experiments/columbia.py
time_restricted_eating_experiments/core.py
time_restricted_eating_experiments-0.3.0.dist-info/LICENSE
time_restricted_eating_experiments-0.3.0.dist-info/METADATA
time_restricted_eating_experiments-0.3.0.dist-info/WHEEL
time_restricted_eating_experiments-0.3.0.dist-info/entry_points.txt
time_restricted_eating_experiments-0.3.0.dist-info/top_level.txt
time_restricted_eating_experiments-0.3.0.dist-info/RECORD
